{
  "id": "3323494",
  "name": "study",
  "font_family": "iconfont",
  "css_prefix_text": "icon-",
  "description": "",
  "glyphs": [
    {
      "icon_id": "20797240",
      "name": "雨水",
      "font_class": "yushui",
      "unicode": "e6c7",
      "unicode_decimal": 59079
    },
    {
      "icon_id": "22334219",
      "name": "开始",
      "font_class": "kaishi2",
      "unicode": "e60b",
      "unicode_decimal": 58891
    },
    {
      "icon_id": "22904112",
      "name": "开始",
      "font_class": "kaishi3",
      "unicode": "e76f",
      "unicode_decimal": 59247
    },
    {
      "icon_id": "1302",
      "name": "加",
      "font_class": "jia",
      "unicode": "e603",
      "unicode_decimal": 58883
    },
    {
      "icon_id": "7425",
      "name": "暂停",
      "font_class": "zanting",
      "unicode": "e605",
      "unicode_decimal": 58885
    },
    {
      "icon_id": "876776",
      "name": "更多",
      "font_class": "gengduo",
      "unicode": "e667",
      "unicode_decimal": 58983
    },
    {
      "icon_id": "980894",
      "name": "暂停",
      "font_class": "weibiaoti519",
      "unicode": "e616",
      "unicode_decimal": 58902
    },
    {
      "icon_id": "999126",
      "name": "更多",
      "font_class": "ai225",
      "unicode": "e6d5",
      "unicode_decimal": 59093
    },
    {
      "icon_id": "1135934",
      "name": "重置",
      "font_class": "reset",
      "unicode": "e611",
      "unicode_decimal": 58897
    },
    {
      "icon_id": "1304889",
      "name": "添加",
      "font_class": "tianjia",
      "unicode": "e622",
      "unicode_decimal": 58914
    },
    {
      "icon_id": "2076214",
      "name": "暂停",
      "font_class": "zanting1",
      "unicode": "e87a",
      "unicode_decimal": 59514
    },
    {
      "icon_id": "2674483",
      "name": "暂停",
      "font_class": "zanting2",
      "unicode": "e629",
      "unicode_decimal": 58921
    },
    {
      "icon_id": "4880426",
      "name": "添加",
      "font_class": "tianjia1",
      "unicode": "e607",
      "unicode_decimal": 58887
    },
    {
      "icon_id": "5301933",
      "name": "暂停",
      "font_class": "zanting3",
      "unicode": "e630",
      "unicode_decimal": 58928
    },
    {
      "icon_id": "5744745",
      "name": "refresh",
      "font_class": "zhongzhi",
      "unicode": "e608",
      "unicode_decimal": 58888
    },
    {
      "icon_id": "6263340",
      "name": "暂停",
      "font_class": "zanting4",
      "unicode": "e669",
      "unicode_decimal": 58985
    },
    {
      "icon_id": "6690009",
      "name": "重置",
      "font_class": "zhongzhi1",
      "unicode": "e63a",
      "unicode_decimal": 58938
    },
    {
      "icon_id": "6732485",
      "name": "重置",
      "font_class": "zhongzhi2",
      "unicode": "e6a8",
      "unicode_decimal": 59048
    },
    {
      "icon_id": "7556179",
      "name": "重置",
      "font_class": "zhongzhi3",
      "unicode": "e606",
      "unicode_decimal": 58886
    },
    {
      "icon_id": "7594152",
      "name": "24gf-pause2",
      "font_class": "24gf-pause2",
      "unicode": "ea81",
      "unicode_decimal": 60033
    },
    {
      "icon_id": "7594156",
      "name": "24gf-pauseSquare",
      "font_class": "24gf-pauseSquare",
      "unicode": "ea82",
      "unicode_decimal": 60034
    },
    {
      "icon_id": "7738373",
      "name": "重置",
      "font_class": "zhongzhi4",
      "unicode": "e60a",
      "unicode_decimal": 58890
    },
    {
      "icon_id": "8094229",
      "name": "重置",
      "font_class": "zhongzhi5",
      "unicode": "e652",
      "unicode_decimal": 58962
    },
    {
      "icon_id": "8334930",
      "name": "重置",
      "font_class": "zhongzhi6",
      "unicode": "e61f",
      "unicode_decimal": 58911
    },
    {
      "icon_id": "10885624",
      "name": "开始",
      "font_class": "kaishi",
      "unicode": "e618",
      "unicode_decimal": 58904
    },
    {
      "icon_id": "11303687",
      "name": "更多",
      "font_class": "gengduo1",
      "unicode": "e621",
      "unicode_decimal": 58913
    },
    {
      "icon_id": "12939972",
      "name": "更多",
      "font_class": "gengduo2",
      "unicode": "e643",
      "unicode_decimal": 58947
    },
    {
      "icon_id": "17654824",
      "name": "暂停",
      "font_class": "zanting5",
      "unicode": "e637",
      "unicode_decimal": 58935
    },
    {
      "icon_id": "17816845",
      "name": "更多",
      "font_class": "gengduo3",
      "unicode": "e609",
      "unicode_decimal": 58889
    },
    {
      "icon_id": "19653499",
      "name": "开始",
      "font_class": "kaishi1",
      "unicode": "e60e",
      "unicode_decimal": 58894
    },
    {
      "icon_id": "998823",
      "name": "更多",
      "font_class": "ai213",
      "unicode": "e6c9",
      "unicode_decimal": 59081
    },
    {
      "icon_id": "1149391",
      "name": "课程表",
      "font_class": "kechengbiao2",
      "unicode": "e6be",
      "unicode_decimal": 59070
    },
    {
      "icon_id": "577398",
      "name": "向下1",
      "font_class": "xiangxia1",
      "unicode": "e771",
      "unicode_decimal": 59249
    },
    {
      "icon_id": "2076270",
      "name": "设置",
      "font_class": "shezhi1",
      "unicode": "e892",
      "unicode_decimal": 59538
    },
    {
      "icon_id": "5387864",
      "name": "关于_o",
      "font_class": "guanyu_o",
      "unicode": "eb77",
      "unicode_decimal": 60279
    },
    {
      "icon_id": "5485659",
      "name": "树列表",
      "font_class": "shuliebiao",
      "unicode": "e617",
      "unicode_decimal": 58903
    },
    {
      "icon_id": "5643514",
      "name": "关于",
      "font_class": "guanyu",
      "unicode": "e604",
      "unicode_decimal": 58884
    },
    {
      "icon_id": "10359985",
      "name": "课程表",
      "font_class": "kechengbiao1",
      "unicode": "e602",
      "unicode_decimal": 58882
    },
    {
      "icon_id": "11372699",
      "name": "时间",
      "font_class": "shijian2",
      "unicode": "e8b8",
      "unicode_decimal": 59576
    },
    {
      "icon_id": "11372771",
      "name": "时间",
      "font_class": "shijian3",
      "unicode": "e8c5",
      "unicode_decimal": 59589
    },
    {
      "icon_id": "11882923",
      "name": "bg-tree",
      "font_class": "bg-tree",
      "unicode": "e648",
      "unicode_decimal": 58952
    },
    {
      "icon_id": "15391360",
      "name": "树",
      "font_class": "shu",
      "unicode": "e61d",
      "unicode_decimal": 58909
    },
    {
      "icon_id": "1135",
      "name": "竖状图",
      "font_class": "shuzhuangtu",
      "unicode": "e600",
      "unicode_decimal": 58880
    },
    {
      "icon_id": "1137",
      "name": "折线图",
      "font_class": "zhexiantu",
      "unicode": "e601",
      "unicode_decimal": 58881
    },
    {
      "icon_id": "421130",
      "name": "扩展属性",
      "font_class": "kuozhanshuxing",
      "unicode": "e690",
      "unicode_decimal": 59024
    },
    {
      "icon_id": "534378",
      "name": "课程表",
      "font_class": "kechengbiao",
      "unicode": "e62c",
      "unicode_decimal": 58924
    },
    {
      "icon_id": "629339",
      "name": "时间",
      "font_class": "shijian",
      "unicode": "e64d",
      "unicode_decimal": 58957
    },
    {
      "icon_id": "658039",
      "name": "时间",
      "font_class": "shijian1",
      "unicode": "e665",
      "unicode_decimal": 58981
    },
    {
      "icon_id": "666885",
      "name": "设置",
      "font_class": "shezhi",
      "unicode": "e68f",
      "unicode_decimal": 59023
    }
  ]
}
